Trekker.cpython-39-darwin.so
Trekker/Trekker.pyx
Trekker/Trekker.pxd
Trekker/Trekker.cpp
Trekker-0.9.dist-info/RECORD
Trekker-0.9.dist-info/LICENSE
Trekker-0.9.dist-info/WHEEL
Trekker-0.9.dist-info/top_level.txt
Trekker-0.9.dist-info/METADATA
