Metadata-Version: 2.1
Name: Trekker
Version: 0.9
Summary: Python package for parallel transport tractography (PTT)
Home-page: https://dmritrekker.github.io/
Author: Dogu Baran Aydogan
Author-email: baran.aydogan@aalto.fi
License: BSD 2-Clause License
Platform: linux
Platform: win
Classifier: Programming Language :: Python :: 3
Classifier: License :: OSI Approved :: BSD License
Classifier: Operating System :: OS Independent
Requires-Python: >=3.6
License-File: LICENSE
